django_rich_logging/__init__.py
django_rich_logging/logging.py
django_rich_logging/objects.py
django_rich_logging-0.3.0.dist-info/LICENSE
django_rich_logging-0.3.0.dist-info/WHEEL
django_rich_logging-0.3.0.dist-info/METADATA
django_rich_logging-0.3.0.dist-info/RECORD
