Metadata-Version: 2.1
Name: django-rich-logging
Version: 0.3.0
Summary: A prettier way to see Django requests while developing.
Home-page: https://github.com/adamghill/django-rich-logging/
License: MIT
Keywords: django,python,static,markdown
Author: adamghill
Author-email: adam@adamghill.com
Requires-Python: >=3.7,<4.0
Classifier: License :: OSI Approved :: MIT License
Classifier: Programming Language :: Python :: 3
Classifier: Programming Language :: Python :: 3.7
Classifier: Programming Language :: Python :: 3.8
Classifier: Programming Language :: Python :: 3.9
Classifier: Programming Language :: Python :: 3.10
Classifier: Programming Language :: Python :: 3.11
Provides-Extra: docs
Requires-Dist: Django (>3.0)
Requires-Dist: Sphinx (>=4.3.2,<5.0.0) ; extra == "docs"
Requires-Dist: attrs (>=21.4.0,<22.0.0) ; extra == "docs"
Requires-Dist: furo (>=2021.11.23,<2022.0.0) ; extra == "docs"
Requires-Dist: linkify-it-py (>=1.0.3,<2.0.0) ; extra == "docs"
Requires-Dist: myst-parser (>=0.16.1,<0.17.0) ; extra == "docs"
Requires-Dist: rich (>11.2.0)
Requires-Dist: sphinx-autobuild (>=2021.3.14,<2022.0.0) ; extra == "docs"
Requires-Dist: sphinx-copybutton (>=0.4.0,<0.5.0) ; extra == "docs"
Requires-Dist: toml ; extra == "docs"
Project-URL: Documentation, https://django-rich-logging.readthedocs.io/
Project-URL: Funding, https://github.com/sponsors/adamghill
Project-URL: Repository, https://github.com/adamghill/django-rich-logging/
